pyscratch/__init__.py
pyscratch/block_name_mapping.csv
pyscratch/main.py
pyscratch/parser.py
pyscratch/scratch.py
pyscratch/scratchtext.ebnf
scratch_python-0.1.3a0.dist-info/LICENSE.txt
scratch_python-0.1.3a0.dist-info/METADATA
scratch_python-0.1.3a0.dist-info/WHEEL
scratch_python-0.1.3a0.dist-info/entry_points.txt
scratch_python-0.1.3a0.dist-info/top_level.txt
scratch_python-0.1.3a0.dist-info/RECORD
